README.txt
setup.py
at/__init__.py
at/at.py
at/tests.py
python_at.egg-info/PKG-INFO
python_at.egg-info/SOURCES.txt
python_at.egg-info/dependency_links.txt
python_at.egg-info/top_level.txt