Metadata-Version: 1.0
Name: python-at
Version: 0.1
Summary: Pythonic wrapper around command-line `at`
Home-page: UNKNOWN
Author: Eddy Mulyono
Author-email: eddymul@gmail.com
License: BSD
Platform: UNKNOWN
